gfnx/__init__.py
gfnx/base.py
gfnx/spaces.py
gfnx/environment/__init__.py
gfnx/environment/amp.py
gfnx/environment/bitseq.py
gfnx/environment/dag.py
gfnx/environment/gfp.py
gfnx/environment/hypergrid.py
gfnx/environment/ising.py
gfnx/environment/phylogenetic_tree.py
gfnx/environment/qm9_small.py
gfnx/environment/sequence.py
gfnx/environment/tfbind.py
gfnx/metrics/__init__.py
gfnx/metrics/approx_distribution.py
gfnx/metrics/base.py
gfnx/metrics/correlation.py
gfnx/metrics/elbo.py
gfnx/metrics/eubo.py
gfnx/metrics/exact_distribution.py
gfnx/metrics/modes.py
gfnx/metrics/reward_delta.py
gfnx/metrics/top_k.py
gfnx/networks/__init__.py
gfnx/networks/reward_models.py
gfnx/networks/transformer.py
gfnx/reward/__init__.py
gfnx/reward/amp.py
gfnx/reward/bitseq.py
gfnx/reward/dag.py
gfnx/reward/dag_likelihood.py
gfnx/reward/dag_prior.py
gfnx/reward/gfp.py
gfnx/reward/hypergrid.py
gfnx/reward/ising.py
gfnx/reward/phylogenetic_tree.py
gfnx/reward/qm9_small.py
gfnx/reward/tfbind.py
gfnx/utils/__init__.py
gfnx/utils/bitseq.py
gfnx/utils/corr.py
gfnx/utils/dag.py
gfnx/utils/distances.py
gfnx/utils/exploration.py
gfnx/utils/ising.py
gfnx/utils/ising_hbpt_sample.py
gfnx/utils/ising_wolf_sample.py
gfnx/utils/masking.py
gfnx/utils/molecules.py
gfnx/utils/phylogenetic_tree.py
gfnx/utils/proteins.py
gfnx/utils/rollout.py
gfnx/visualize/__init__.py
gfnx/visualize/hypergrid.py
gfnx/visualize/sequence.py
gfnx/visualize/visualizer.py
gfnx-0.0.1.dist-info/METADATA
gfnx-0.0.1.dist-info/WHEEL
gfnx-0.0.1.dist-info/licenses/LICENCE
gfnx-0.0.1.dist-info/RECORD
