Metadata-Version: 2.4
Name: gfnx
Version: 0.0.1
Summary: Environments for Generative Flow Networks in JAX
Project-URL: Homepage, https://github.com/d-tiapkin/gfnx
Project-URL: Issues, https://github.com/d-tiapkin/gfnx/issues
Author: Daniil Tiapkin, Arten Agarkov, Nikita Morozov, Ian Maksimov, Timofei Gritsaev, Sergey Samsonov
License-Expression: MIT
License-File: LICENCE
Classifier: Operating System :: OS Independent
Classifier: Programming Language :: Python :: 3
Requires-Python: >=3.10
Requires-Dist: chex
Requires-Dist: flashbax
Requires-Dist: jax-tqdm
Requires-Dist: jax>=0.4.27.0
Requires-Dist: jaxlib>=0.4.27.0
Requires-Dist: jaxtyping
Requires-Dist: matplotlib
Requires-Dist: networkx
Requires-Dist: numpy==1.26.4
Requires-Dist: omegaconf
Provides-Extra: baselines
Requires-Dist: equinox; extra == 'baselines'
Requires-Dist: flashbax; extra == 'baselines'
Requires-Dist: hydra-core; extra == 'baselines'
Requires-Dist: jax-tqdm; extra == 'baselines'
Requires-Dist: jraph; extra == 'baselines'
Requires-Dist: optax; extra == 'baselines'
Requires-Dist: orbax-checkpoint; extra == 'baselines'
Requires-Dist: pillow; extra == 'baselines'
Requires-Dist: wandb; extra == 'baselines'
Provides-Extra: tests
Requires-Dist: equinox; extra == 'tests'
Requires-Dist: pytest; extra == 'tests'
